{
  "version": "6",
  "dialect": "sqlite",
  "id": "ebab6e6e-6119-4fee-9691-2154dc620089",
  "prevId": "00000000-0000-0000-0000-000000000000",
  "tables": {
    "countries": {
      "name": "countries",
      "columns": {
        "id": {
          "name": "id",
          "type": "integer",
          "primaryKey": true,
          "notNull": true,
          "autoincrement": false
        },
        "code": {
          "name": "code",
          "type": "text",
          "primaryKey": false,
          "notNull": false,
          "autoincrement": false
        },
        "text": {
          "name": "text",
          "type": "text",
          "primaryKey": false,
          "notNull": false,
          "autoincrement": false
        }
      },
      "indexes": {
        "countries_code_unique": {
          "name": "countries_code_unique",
          "columns": [
            "code"
          ],
          "isUnique": true
        }
      },
      "foreignKeys": {},
      "compositePrimaryKeys": {},
      "uniqueConstraints": {},
      "checkConstraints": {}
    }
  },
  "views": {},
  "enums": {},
  "_meta": {
    "schemas": {},
    "tables": {},
    "columns": {}
  },
  "internal": {
    "indexes": {}
  }
}